{"name":"build-javascript","namedChunkGroups":{"polyfill":{"name":"polyfill","assets":[{"name":"webpack-runtime-1c4a73308005a1ef8964.js","size":4582},{"name":"polyfill-d2aa6adce2b3dc4c24d6.js","size":85856}],"filteredAssets":0,"assetsSize":90438,"filteredAuxiliaryAssets":2,"auxiliaryAssetsSize":225984},"app":{"name":"app","assets":[{"name":"webpack-runtime-1c4a73308005a1ef8964.js","size":4582},{"name":"framework-fd8c2f31b9eeffed3beb.js","size":129769},{"name":"app-99ab2420ba9b054785d4.js","size":53912}],"filteredAssets":0,"assetsSize":188263,"filteredAuxiliaryAssets":3,"auxiliaryAssetsSize":561910},"component---src-pages-404-js":{"name":"component---src-pages-404-js","assets":[{"name":"styles.98d36bf7dc2b0a59e511.css","size":24434},{"name":"commons-b85f10cc41de9405415b.js","size":19425},{"name":"component---src-pages-404-js-1b20829fe71d4a888774.js","size":651}],"filteredAssets":0,"assetsSize":44510,"filteredAuxiliaryAssets":28,"auxiliaryAssetsSize":7260805},"component---src-pages-contact-success-js":{"name":"component---src-pages-contact-success-js","assets":[{"name":"styles.98d36bf7dc2b0a59e511.css","size":24434},{"name":"commons-b85f10cc41de9405415b.js","size":19425},{"name":"component---src-pages-contact-success-js-32de3aa7a9fd66e26b66.js","size":810}],"filteredAssets":0,"assetsSize":44669,"filteredAuxiliaryAssets":28,"auxiliaryAssetsSize":7261013},"component---src-pages-index-js":{"name":"component---src-pages-index-js","assets":[{"name":"styles.98d36bf7dc2b0a59e511.css","size":24434},{"name":"commons-b85f10cc41de9405415b.js","size":19425},{"name":"component---src-pages-index-js-b91a426e06efdde945ce.js","size":39186}],"filteredAssets":0,"assetsSize":83045,"filteredAuxiliaryAssets":28,"auxiliaryAssetsSize":7405435},"component---src-pages-legal-js":{"name":"component---src-pages-legal-js","assets":[{"name":"styles.98d36bf7dc2b0a59e511.css","size":24434},{"name":"commons-b85f10cc41de9405415b.js","size":19425},{"name":"component---src-pages-legal-js-c9bfb7ad580fee3902b4.js","size":1389}],"filteredAssets":0,"assetsSize":45248,"filteredAuxiliaryAssets":28,"auxiliaryAssetsSize":7261889},"component---src-pages-privacy-js":{"name":"component---src-pages-privacy-js","assets":[{"name":"styles.98d36bf7dc2b0a59e511.css","size":24434},{"name":"commons-b85f10cc41de9405415b.js","size":19425},{"name":"component---src-pages-privacy-js-27e78bc51cf1b6fe7bf0.js","size":21462}],"filteredAssets":0,"assetsSize":65321,"filteredAuxiliaryAssets":28,"auxiliaryAssetsSize":7290275}},"assetsByChunkName":{"polyfill":["webpack-runtime-1c4a73308005a1ef8964.js","polyfill-d2aa6adce2b3dc4c24d6.js"],"app":["webpack-runtime-1c4a73308005a1ef8964.js","framework-fd8c2f31b9eeffed3beb.js","app-99ab2420ba9b054785d4.js"],"component---src-pages-404-js":["styles.98d36bf7dc2b0a59e511.css","commons-b85f10cc41de9405415b.js","component---src-pages-404-js-1b20829fe71d4a888774.js"],"component---src-pages-contact-success-js":["styles.98d36bf7dc2b0a59e511.css","commons-b85f10cc41de9405415b.js","component---src-pages-contact-success-js-32de3aa7a9fd66e26b66.js"],"component---src-pages-index-js":["styles.98d36bf7dc2b0a59e511.css","commons-b85f10cc41de9405415b.js","component---src-pages-index-js-b91a426e06efdde945ce.js"],"component---src-pages-legal-js":["styles.98d36bf7dc2b0a59e511.css","commons-b85f10cc41de9405415b.js","component---src-pages-legal-js-c9bfb7ad580fee3902b4.js"],"component---src-pages-privacy-js":["styles.98d36bf7dc2b0a59e511.css","commons-b85f10cc41de9405415b.js","component---src-pages-privacy-js-27e78bc51cf1b6fe7bf0.js"]},"childAssetsByChunkName":{}}